mycalc/calculator.py
seungji-0.0.1.dist-info/METADATA
seungji-0.0.1.dist-info/WHEEL
seungji-0.0.1.dist-info/top_level.txt
seungji-0.0.1.dist-info/RECORD
