Metadata-Version: 2.1
Name: seungji
Version: 0.0.1
Summary: oss calculator
Home-page: https://github.com/ChaeSeungJi/mycalc
Download-URL: https://github.com/ChaeSeungJi/mycalc/archive/refs/heads/main.zip
Author: Seungji
Author-email: 1924245@donga.ac.kr
License: UNKNOWN
Platform: UNKNOWN
Classifier: Programming Language :: Python :: 3
